drydock/construction.py
drydock/drydock.py
drydock/duster.py
drydock/report.py
drydock/templates.py
drydock/__init__.py
drydock-0.6.10.dist-info/DESCRIPTION.rst
drydock-0.6.10.dist-info/entry_points.txt
drydock-0.6.10.dist-info/METADATA
drydock-0.6.10.dist-info/metadata.json
drydock-0.6.10.dist-info/RECORD
drydock-0.6.10.dist-info/top_level.txt
drydock-0.6.10.dist-info/WHEEL
