Metadata-Version: 2.0
Name: drydock
Version: 0.6.10
Summary: A Docker cluster construction utility.
Home-page: https://github.com/Nekroze/drydock
Author: Taylor "Nekroze" Lawson
Author-email: nekroze@eturnilnetwork.com
License: MIT
Keywords: drydock
Platform: UNKNOWN
Classifier: Development Status :: 2 - Pre-Alpha
Classifier: Intended Audience :: Developers
Classifier: License :: OSI Approved :: MIT License
Classifier: Natural Language :: English
Classifier: Programming Language :: Python :: 2
Classifier: Programming Language :: Python :: 2.6
Classifier: Programming Language :: Python :: 2.7
Classifier: Programming Language :: Python :: 3
Classifier: Programming Language :: Python :: 3.3
Classifier: Programming Language :: Python :: Implementation :: PyPy
Requires-Dist: pyyaml (>=3.10)
Requires-Dist: docopt (>=0.6.1)
Requires-Dist: six (>=1.5.2)
Requires-Dist: docker-py (>=0.3.0)
